MANIFEST.in
README.txt
setup.cfg
setup.py
docs/HISTORY.txt
horae/__init__.py
horae.core.egg-info/PKG-INFO
horae.core.egg-info/SOURCES.txt
horae.core.egg-info/dependency_links.txt
horae.core.egg-info/entry_points.txt
horae.core.egg-info/namespace_packages.txt
horae.core.egg-info/not-zip-safe
horae.core.egg-info/requires.txt
horae.core.egg-info/top_level.txt
horae/core/__init__.py
horae/core/configuration.py
horae/core/configure.zcml
horae/core/container.py
horae/core/currency.py
horae/core/deferred.py
horae/core/idmanager.py
horae/core/interfaces.py
horae/core/location.py
horae/core/service.py
horae/core/size.py
horae/core/upgrade.py
horae/core/utils.py
horae/core/vocabulary.py
horae/core/locales/horae.core.pot
horae/core/locales/de/LC_MESSAGES/horae.core.mo
horae/core/locales/de/LC_MESSAGES/horae.core.po