Metadata-Version: 1.0
Name: horae.core
Version: 1.0a1
Summary: Basic functionality for Horae
Home-page: UNKNOWN
Author: Simon Kaeser
Author-email: skaeser@gmail.com
License: GPL
Platform: UNKNOWN
Classifier: Programming Language :: Python
Classifier: Topic :: Software Development :: Libraries :: Python Modules
